pytest_rng/__init__.py
pytest_rng/plugin.py
pytest_rng/version.py
pytest_rng/tests/__init__.py
pytest_rng/tests/test_fixtures.py
pytest_rng/tests/test_pytest.py
pytest_rng-1.0.0.dist-info/LICENSE.rst
pytest_rng-1.0.0.dist-info/METADATA
pytest_rng-1.0.0.dist-info/WHEEL
pytest_rng-1.0.0.dist-info/entry_points.txt
pytest_rng-1.0.0.dist-info/top_level.txt
pytest_rng-1.0.0.dist-info/RECORD
