Metadata-Version: 2.1
Name: pytest-rng
Version: 1.0.0
Summary: Fixtures for seeding tests and making randomness reproducible
Home-page: https://www.nengo.ai/pytest-rng
Author: Applied Brain Research
Author-email: info@appliedbrainresearch.com
License: MIT license
Platform: UNKNOWN
Classifier: Development Status :: 5 - Production/Stable
Classifier: Framework :: Pytest
Classifier: License :: OSI Approved :: MIT License
Classifier: Programming Language :: Python :: 3 :: Only
Classifier: Programming Language :: Python :: 3.5
Classifier: Programming Language :: Python :: 3.6
Classifier: Programming Language :: Python :: 3.7
Requires-Python: >=3.5
Requires-Dist: numpy
Requires-Dist: pytest
Provides-Extra: all
Requires-Dist: nengo-sphinx-theme (>=1.0) ; extra == 'all'
Requires-Dist: sphinx ; extra == 'all'
Provides-Extra: docs
Requires-Dist: nengo-sphinx-theme (>=1.0) ; extra == 'docs'
Requires-Dist: sphinx ; extra == 'docs'
Provides-Extra: optional
Provides-Extra: tests
